// converted by version 1.2
// on Fri Nov 29 03:54:04 CET 2019

.package com/metadatamanipulation {
	.aid 0xA0:0x0:0x0:0x0:0xAA;
	.version 0.0;

	.imports {
		0xA0:0x0:0x0:0x0:0x62:0x1:0x1 1.0;		//javacard/framework
	}

	.applet {
		0xA0:0x0:0x0:0x0:0xAA:0x55:0x1 MetadataManipulation;
	}

	.constantPool {
		// 0
		instanceFieldRef byte[] MetadataManipulation/success;
		// 1
		instanceFieldRef byte[] MetadataManipulation/failure;
		// 2
		instanceFieldRef short MetadataManipulation/msgLen;
		// 3
		instanceFieldRef byte[] MetadataManipulation/mem;
		// 4
		instanceFieldRef byte[] MetadataManipulation/file;
		// 5
		staticMethodRef 0.3.0()V;		// javacard/framework/Applet.<init>()V
		// 6
		staticMethodRef MetadataManipulation/<init>([BSB)V;
		// 7
		classRef MetadataManipulation;
		// 8
		virtualMethodRef 0.3.1()V;		// javacard/framework/Applet.register()V
		// 9
		virtualMethodRef 0.10.1()[B;		// javacard/framework/APDU.getBuffer()[B
		// 10
		virtualMethodRef 0.3.3()Z;		// javacard/framework/Applet.selectingApplet()Z
		// 11
		staticMethodRef 0.7.1(S)V;		// javacard/framework/ISOException.throwIt(S)V
		// 12
		staticMethodRef MetadataManipulation/addr([B)S;
		// 13
		staticMethodRef MetadataManipulation/ptr(S)[B;
		// 14
		staticMethodRef 0.16.6([BSS)S;		// javacard/framework/Util.setShort([BSS)S
		// 15
		virtualMethodRef 0.10.8(SS)V;		// javacard/framework/APDU.setOutgoingAndSend(SS)V
		// 16
		staticMethodRef 0.16.2([BS[BSS)S;		// javacard/framework/Util.arrayCopyNonAtomic([BS[BSS)S
	}

	.class public MetadataManipulation 0 extends 0.3 {		// extends javacard/framework/Applet

		.fields {
			 byte[] success 0;		// [B
			 byte[] failure 1;		// [B
			 byte[] mem 2;		// [B
			 byte[] file 3;		// [B
			 short msgLen 4;		// S
			protected static final byte CLA_APP = -96;		// B
			protected static final byte INS_PATCH = -76;		// B
			private static final byte INS_SUCCESS = 1;		// B
			private static final byte INS_FAILURE = 2;		// B
		}

		.publicMethodTable 7 {
			equals(Ljava/lang/Object;)Z;
			register()V;
			register([BSB)V;
			selectingApplet()Z;
			deselect()V;
			getShareableInterfaceObject(Ljavacard/framework/AID;B)Ljavacard/framework/Shareable;;
			select()Z;
			process(Ljavacard/framework/APDU;)V;
		}

		.packageMethodTable 0 {
		}

		.method public static install([BSB)V 0 {
			.stack 5;
			.locals 0;

				L0:	new 7;		// com/metadatamanipulation/MetadataManipulation
					dup;
					aload_0;
					sload_1;
					sload_2;
					invokespecial 6;		// com/metadatamanipulation/MetadataManipulation.<init>([BSB)V
					pop;
					return;
		}

		.method protected <init>([BSB)V 1 {
			.stack 5;
			.locals 0;

				L0:	aload_0;
					invokespecial 5;		// javacard/framework/Applet.<init>()V
					aload_0;
					sconst_4;
					newarray 11;
					dup;
					sconst_0;
					sconst_1;
					bastore;
					dup;
					sconst_1;
					sconst_2;
					bastore;
					dup;
					sconst_2;
					sconst_1;
					bastore;
					dup;
					sconst_3;
					sconst_2;
					bastore;
					putfield_a 0;		// reference com/metadatamanipulation/MetadataManipulation.success
					aload_0;
					sconst_4;
					newarray 11;
					dup;
					sconst_0;
					bspush -128;
					bastore;
					dup;
					sconst_1;
					bspush 64;
					bastore;
					dup;
					sconst_2;
					bspush -128;
					bastore;
					dup;
					sconst_3;
					bspush 64;
					bastore;
					putfield_a 1;		// reference com/metadatamanipulation/MetadataManipulation.failure
					aload_0;
					sconst_4;
					putfield_s 2;		// short com/metadatamanipulation/MetadataManipulation.msgLen
					aload_0;
					sconst_4;
					newarray 11;
					dup;
					sconst_0;
					bspush 127;
					bastore;
					dup;
					sconst_1;
					sconst_m1;
					bastore;
					dup;
					sconst_2;
					sconst_1;
					bastore;
					dup;
					sconst_3;
					sconst_0;
					bastore;
					putfield_a 3;		// reference com/metadatamanipulation/MetadataManipulation.mem
					aload_0;
					getfield_a_this 3;		// reference com/metadatamanipulation/MetadataManipulation.mem
					putfield_a 4;		// reference com/metadatamanipulation/MetadataManipulation.file
					aload_0;
					invokevirtual 8;		// javacard/framework/Applet.register()V
					return;
		}

		.method public process(Ljavacard/framework/APDU;)V 7 {
			.stack 5;
			.locals 5;

			.descriptor	Ljavacard/framework/APDU;	0.10;

				L0:	aload_1;
					invokevirtual 9;		// javacard/framework/APDU.getBuffer()[B
					astore_2;
					aload_0;
					invokevirtual 10;		// javacard/framework/Applet.selectingApplet()Z
					ifeq L2;
				L1:	return;
				L2:	aload_2;
					sconst_0;
					baload;
					bspush -96;
					if_scmpeq L4;
				L3:	sspush 28160;
					invokestatic 11;		// javacard/framework/ISOException.throwIt(S)V
				L4:	aload_2;
					sconst_1;
					baload;
					slookupswitch L8 3 -76 L5 1 L6 2 L7;
				L5:	aload_0;
					getfield_a_this 3;		// reference com/metadatamanipulation/MetadataManipulation.mem
					invokestatic 12;		// com/metadatamanipulation/MetadataManipulation.addr([B)S
					sconst_4;
					sadd;
					invokestatic 13;		// com/metadatamanipulation/MetadataManipulation.ptr(S)[B
					putfield_a 4;		// reference com/metadatamanipulation/MetadataManipulation.file
					aload_2;
					sconst_0;
					getfield_a_this 4;		// reference com/metadatamanipulation/MetadataManipulation.file
					arraylength;
					invokestatic 14;		// javacard/framework/Util.setShort([BSS)S
					pop;
					aload_1;
					sconst_0;
					sconst_2;
					invokevirtual 15;		// javacard/framework/APDU.setOutgoingAndSend(SS)V
					goto L9;
				L6:	getfield_a_this 0;		// reference com/metadatamanipulation/MetadataManipulation.success
					sconst_0;
					aload_2;
					sconst_0;
					getfield_s_this 2;		// short com/metadatamanipulation/MetadataManipulation.msgLen
					invokestatic 16;		// javacard/framework/Util.arrayCopyNonAtomic([BS[BSS)S
					pop;
					aload_1;
					sconst_0;
					sconst_4;
					invokevirtual 15;		// javacard/framework/APDU.setOutgoingAndSend(SS)V
					goto L9;
				L7:	getfield_a_this 1;		// reference com/metadatamanipulation/MetadataManipulation.failure
					sconst_0;
					aload_2;
					sconst_0;
					getfield_s_this 2;		// short com/metadatamanipulation/MetadataManipulation.msgLen
					invokestatic 16;		// javacard/framework/Util.arrayCopyNonAtomic([BS[BSS)S
					pop;
					aload_1;
					sconst_0;
					sconst_4;
					invokevirtual 15;		// javacard/framework/APDU.setOutgoingAndSend(SS)V
					goto L9;
				L8:	sspush 27904;
					invokestatic 11;		// javacard/framework/ISOException.throwIt(S)V
				L9:	return;
		}

		.method public static addr([B)S 2 {
			.stack 1;
			.locals 0;

				//L0:	sconst_0;
				L0:	sload_0;
					sreturn;
		}

		.method public static addrHelper(S)S 3 {
			.stack 1;
			.locals 0;

				L0:	sload_0;
					sreturn;
		}

		.method public static ptr(S)[B 4 {
			.stack 1;
			.locals 0;

				//L0:	aconst_null;
				L0:	aload_0;
					areturn;
		}

		.method public static ptrHelper([B)[B 5 {
			.stack 1;
			.locals 0;

				L0:	aload_0;
					areturn;
		}

	}

}
