// converted by version 1.3
// on Wed Apr 15 16:48:37 CEST 2020

.package com/se/applets {
	.aid 0xA0:0x0:0x0:0x0:0x62:0x3:0x1:0xC:0x1;
	.version 0.0;

	.imports {
		0xA0:0x0:0x0:0x0:0x62:0x1:0x1 1.2;		//javacard/framework
		0xA0:0x0:0x0:0x0:0x62:0x3:0x1:0xC:0x2 0.0;		//com/se/vulns
	}

	.applet {
		0xA0:0x0:0x0:0x0:0x62:0x3:0x1:0xC:0x1:0x1 SEApplet;
	}

	.constantPool {
		// 0
		staticMethodRef 0.3.0()V;		// javacard/framework/Applet.<init>()V
		// 1
		virtualMethodRef 0.3.1()V;		// javacard/framework/Applet.register()V
		// 2
		classRef SEApplet;
		// 3
		staticMethodRef SEApplet/<init>()V;
		// 4
		virtualMethodRef 0.10.1()[B;		// javacard/framework/APDU.getBuffer()[B
		// 5
		virtualMethodRef 0.10.6()S;		// javacard/framework/APDU.setIncomingAndReceive()S
		// 6
		staticMethodRef 0.7.1(S)V;		// javacard/framework/ISOException.throwIt(S)V
		// 7
		virtualMethodRef 0.10.7()S;		// javacard/framework/APDU.setOutgoing()S
		// 8
		virtualMethodRef 0.10.9(S)V;		// javacard/framework/APDU.setOutgoingLength(S)V
		// 9
		virtualMethodRef 0.10.4(SS)V;		// javacard/framework/APDU.sendBytes(SS)V
		// 10
		virtualMethodRef SEApplet/get_req(Ljavacard/framework/APDU;S)[B;
			.descriptor	Ljavacard/framework/APDU;	0.10;

		// 11
		staticMethodRef 1.0.1()S;		// com/se/vulns/Test.get_static()S
		// 12
		virtualMethodRef SEApplet/send_resp(Ljavacard/framework/APDU;S)V;
			.descriptor	Ljavacard/framework/APDU;	0.10;

		// 13
		virtualMethodRef SEApplet/get_static(Ljavacard/framework/APDU;)V;
			.descriptor	Ljavacard/framework/APDU;	0.10;

	}

	.class public SEApplet 0 extends 0.3 {		// extends javacard/framework/Applet

		.fields {
			private static final byte SEApplet_CLA = -128;		// B
			private static final byte GET_STATIC = 16;		// B
		}

		.publicMethodTable 7 {
			equals(Ljava/lang/Object;)Z;
			register()V;
			register([BSB)V;
			selectingApplet()Z;
			deselect()V;
			getShareableInterfaceObject(Ljavacard/framework/AID;B)Ljavacard/framework/Shareable;;
			select()Z;
			process(Ljavacard/framework/APDU;)V;
			get_req(Ljavacard/framework/APDU;S)[B;
			send_resp(Ljavacard/framework/APDU;S)V;
			get_static(Ljavacard/framework/APDU;)V;
		}

		.packageMethodTable 0 {
		}

		.method protected <init>()V 0 {
			.stack 1;
			.locals 0;

				L0:	aload_0;
					invokespecial 0;		// javacard/framework/Applet.<init>()V
					aload_0;
					invokevirtual 1;		// javacard/framework/Applet.register()V
					return;
		}

		.method public static install([BSB)V 1 {
			.stack 2;
			.locals 0;

				L0:	new 2;		// com/se/applets/SEApplet
					dup;
					invokespecial 3;		// com/se/applets/SEApplet.<init>()V
					pop;
					return;
		}

		.method public get_req(Ljavacard/framework/APDU;S)[B 8 {
			.stack 2;
			.locals 3;

			.descriptor	Ljavacard/framework/APDU;	0.10;

				L0:	aload_1;
					invokevirtual 4;		// javacard/framework/APDU.getBuffer()[B
					astore_3;
					aload_3;
					sconst_4;
					baload;
					sstore 4;
					aload_1;
					invokevirtual 5;		// javacard/framework/APDU.setIncomingAndReceive()S
					s2b;
					sstore 5;
					sload 4;
					sload_2;
					if_scmpne L2;
				L1:	sload 5;
					sload_2;
					if_scmpeq L3;
				L2:	sspush 26368;
					invokestatic 6;		// javacard/framework/ISOException.throwIt(S)V
				L3:	aload_3;
					areturn;
		}

		.method public send_resp(Ljavacard/framework/APDU;S)V 9 {
			.stack 3;
			.locals 1;

			.descriptor	Ljavacard/framework/APDU;	0.10;

				L0:	aload_1;
					invokevirtual 7;		// javacard/framework/APDU.setOutgoing()S
					sstore_3;
					sload_3;
					sload_2;
					if_scmpge L2;
				L1:	sspush 26368;
					invokestatic 6;		// javacard/framework/ISOException.throwIt(S)V
				L2:	aload_1;
					sload_2;
					s2b;
					invokevirtual 8;		// javacard/framework/APDU.setOutgoingLength(S)V
					aload_1;
					sconst_5;
					sload_2;
					invokevirtual 9;		// javacard/framework/APDU.sendBytes(SS)V
					return;
		}

		.method public get_static(Ljavacard/framework/APDU;)V 10 {
			.stack 4;
			.locals 2;

			.descriptor	Ljavacard/framework/APDU;	0.10;

				L0:	aload_0;
					aload_1;
					sconst_1;
					invokevirtual 10;		// com/se/applets/SEApplet.get_req(Ljavacard/framework/APDU;S)[B
					astore_2;
					invokestatic 11;		// com/se/vulns/Test.get_static()S
					sstore_3;
					aload_2;
					sconst_5;
					sload_3;
					bspush 8;
					sshr;
					sspush 255;
					sand;
					s2b;
					bastore;
					aload_2;
					bspush 6;
					sload_3;
					sspush 255;
					sand;
					s2b;
					bastore;
					aload_0;
					aload_1;
					sconst_2;
					invokevirtual 12;		// com/se/applets/SEApplet.send_resp(Ljavacard/framework/APDU;S)V
					return;
		}

		.method public process(Ljavacard/framework/APDU;)V 7 {
			.stack 2;
			.locals 1;

			.descriptor	Ljavacard/framework/APDU;	0.10;

				L0:	aload_1;
					invokevirtual 4;		// javacard/framework/APDU.getBuffer()[B
					astore_2;
					aload_2;
					sconst_0;
					baload;
					bspush -128;
					if_scmpeq L2;
				L1:	sspush 28160;
					invokestatic 6;		// javacard/framework/ISOException.throwIt(S)V
				L2:	aload_2;
					sconst_1;
					baload;
					slookupswitch L4 1 16 L3;
				L3:	aload_0;
					aload_1;
					invokevirtual 13;		// com/se/applets/SEApplet.get_static(Ljavacard/framework/APDU;)V
					return;
				L4:	sspush 27904;
					invokestatic 6;		// javacard/framework/ISOException.throwIt(S)V
					return;
		}

	}

}
