// converted by version  [v3.0.4]
// on Wed Apr 15 13:02:43 CEST 2020

.package com/se/applets {
	.aid 0xA0:0x0:0x0:0x0:0x62:0x3:0x1:0xC:0x1;
	.version 0.0;

	.imports {
		0xA0:0x0:0x0:0x0:0x62:0x1:0x1 1.5;		//javacard/framework
		0xA0:0x0:0x0:0x0:0x62:0x3:0x1:0xC:0x2 0.0;		//com/se/vulns
		0xA0:0x0:0x0:0x0:0x62:0x0:0x1 1.0;		//java/lang
	}

	.applet {
		0xA0:0x0:0x0:0x0:0x62:0x3:0x1:0xC:0x1:0x1 SEApplet;
	}

	.constantPool {
		// 0
		instanceFieldRef byte[] SEApplet/bmem;
		// 1
		instanceFieldRef int[] SEApplet/imem;
		// 2
		.classRef SEApplet;
		// 3
		staticMethodRef SEApplet/<init>()V;
		// 4
		staticMethodRef 0.3.0()V;		// javacard/framework/Applet.<init>()V
		// 5
		staticFieldRef byte SEApplet/expidx;
		// 6
		staticMethodRef 1.0.2()[B;		// com/se/vulns/Cast.bmem()[B
		// 7
		virtualMethodRef 0.3.1()V;		// register()V
		// 8
		staticMethodRef 1.0.3()[I;		// com/se/vulns/Cast.imem()[I
		// 9
		staticMethodRef 1.0.4()V;		// com/se/vulns/Cast.cleanup()V
		// 10
		virtualMethodRef 0.10.1()[B;		// getBuffer()[B
		// 11
		virtualMethodRef 0.10.6()S;		// setIncomingAndReceive()S
		// 12
		staticMethodRef 0.7.1(S)V;		// javacard/framework/ISOException.throwIt(S)V
		// 13
		virtualMethodRef 0.10.7()S;		// setOutgoing()S
		// 14
		virtualMethodRef 0.10.9(S)V;		// setOutgoingLength(S)V
		// 15
		virtualMethodRef 0.10.4(SS)V;		// sendBytes(SS)V
		// 16
		virtualMethodRef SEApplet/get_req(Ljavacard/framework/APDU;S)[B;
			.descriptor	Ljavacard/framework/APDU;	0.10;

		// 17
		virtualMethodRef SEApplet/send_resp(Ljavacard/framework/APDU;S)V;
			.descriptor	Ljavacard/framework/APDU;	0.10;

		// 18
		virtualMethodRef SEApplet/bmem()[B;
		// 19
		virtualMethodRef SEApplet/imem()[I;
		// 20
		virtualMethodRef SEApplet/cleanup()V;
		// 21
		virtualMethodRef 0.3.3()Z;		// selectingApplet()Z
		// 22
		virtualMethodRef SEApplet/ping(Ljavacard/framework/APDU;)V;
			.descriptor	Ljavacard/framework/APDU;	0.10;

		// 23
		virtualMethodRef SEApplet/status(Ljavacard/framework/APDU;)V;
			.descriptor	Ljavacard/framework/APDU;	0.10;

		// 24
		virtualMethodRef SEApplet/setup(Ljavacard/framework/APDU;)V;
			.descriptor	Ljavacard/framework/APDU;	0.10;

		// 25
		virtualMethodRef SEApplet/read_mem(Ljavacard/framework/APDU;)V;
			.descriptor	Ljavacard/framework/APDU;	0.10;

		// 26
		virtualMethodRef SEApplet/write_mem(Ljavacard/framework/APDU;)V;
			.descriptor	Ljavacard/framework/APDU;	0.10;

		// 27
		virtualMethodRef SEApplet/cleanup(Ljavacard/framework/APDU;)V;
			.descriptor	Ljavacard/framework/APDU;	0.10;

	}

	.class public SEApplet 0 extends 0.3 {		// extends javacard/framework/Applet

		.fields {
			private byte[] bmem 0;		// [B
			private int[] imem 1;		// [I
			private static final byte SEApplet_CLA = -128;		// B
			private static final byte PING = 16;		// B
			private static final byte STATUS = 17;		// B
			private static final byte SETUP = 18;		// B
			private static final byte READ_MEM = 19;		// B
			private static final byte WRITE_MEM = 20;		// B
			private static final byte CLEANUP = 21;		// B
			private static final short BUFLEN = 64;		// S
			private static byte expidx = 1;		// B
		}

		.publicMethodTable 7 {
			equals(Ljava/lang/Object;)Z;
			register()V;
			register([BSB)V;
			selectingApplet()Z;
			deselect()V;
			getShareableInterfaceObject(Ljavacard/framework/AID;B)Ljavacard/framework/Shareable;;
			select()Z;
			process(Ljavacard/framework/APDU;)V;
			bmem()[B;
			imem()[I;
			cleanup()V;
			get_req(Ljavacard/framework/APDU;S)[B;
			send_resp(Ljavacard/framework/APDU;S)V;
			ping(Ljavacard/framework/APDU;)V;
			status(Ljavacard/framework/APDU;)V;
			setup(Ljavacard/framework/APDU;)V;
			read_mem(Ljavacard/framework/APDU;)V;
			write_mem(Ljavacard/framework/APDU;)V;
			cleanup(Ljavacard/framework/APDU;)V;
		}

		.packageMethodTable 0 {
		}

		.method protected <init>()V 0 {
			.stack 1;
			.locals 0;

				L0:	aload_0;
					invokespecial 4;		// javacard/framework/Applet.<init>()V
					aload_0;
					invokevirtual 7;		// register()V
					return;
		}

		.method public static install([BSB)V 1 {
			.stack 2;
			.locals 0;

				L0:	new 2;		// com/se/applets/SEApplet
					dup;
					invokespecial 3;		// com/se/applets/SEApplet.<init>()V
					pop;
					return;
		}

		.method public bmem()[B 8 {
			.stack 2;
			.locals 0;

				L0:	getfield_a_this 0;		// reference com/se/applets/SEApplet.bmem
					ifnonnull L3;
				L1:	getstatic_b 5;		// byte com/se/applets/SEApplet.expidx
					slookupswitch L3 1 1 L2;
				L2:	aload_0;
					invokestatic 6;		// com/se/vulns/Cast.bmem()[B
					putfield_a 0;		// reference com/se/applets/SEApplet.bmem
				L3:	getfield_a_this 0;		// reference com/se/applets/SEApplet.bmem
					areturn;
		}

		.method public imem()[I 9 {
			.stack 2;
			.locals 0;

				L0:	getfield_a_this 1;		// reference com/se/applets/SEApplet.imem
					ifnonnull L3;
				L1:	getstatic_b 5;		// byte com/se/applets/SEApplet.expidx
					slookupswitch L3 1 1 L2;
				L2:	aload_0;
					invokestatic 8;		// com/se/vulns/Cast.imem()[I
					putfield_a 1;		// reference com/se/applets/SEApplet.imem
				L3:	getfield_a_this 1;		// reference com/se/applets/SEApplet.imem
					areturn;
		}

		.method public cleanup()V 10 {
			.stack 1;
			.locals 0;

				L0:	getfield_a_this 1;		// reference com/se/applets/SEApplet.imem
					ifnull L3;
				L1:	getstatic_b 5;		// byte com/se/applets/SEApplet.expidx
					slookupswitch L3 1 1 L2;
				L2:	invokestatic 9;		// com/se/vulns/Cast.cleanup()V
				L3:	return;
		}

		.method public get_req(Ljavacard/framework/APDU;S)[B 11 {
			.stack 2;
			.locals 3;

			.descriptor	Ljavacard/framework/APDU;	0.10;

				L0:	aload_1;
					invokevirtual 10;		// getBuffer()[B
					astore_3;
					aload_3;
					sconst_4;
					baload;
					sstore 4;
					aload_1;
					invokevirtual 11;		// setIncomingAndReceive()S
					s2b;
					sstore 5;
					sload 4;
					sload_2;
					if_scmpne L2;
				L1:	sload 5;
					sload_2;
					if_scmpeq L3;
				L2:	sspush 26368;
					invokestatic 12;		// javacard/framework/ISOException.throwIt(S)V
				L3:	aload_3;
					areturn;
		}

		.method public send_resp(Ljavacard/framework/APDU;S)V 12 {
			.stack 3;
			.locals 1;

			.descriptor	Ljavacard/framework/APDU;	0.10;

				L0:	aload_1;
					invokevirtual 13;		// setOutgoing()S
					sstore_3;
					sload_3;
					sload_2;
					if_scmpge L2;
				L1:	sspush 26368;
					invokestatic 12;		// javacard/framework/ISOException.throwIt(S)V
				L2:	aload_1;
					sload_2;
					s2b;
					invokevirtual 14;		// setOutgoingLength(S)V
					aload_1;
					sconst_5;
					sload_2;
					invokevirtual 15;		// sendBytes(SS)V
					return;
		}

		.method public ping(Ljavacard/framework/APDU;)V 13 {
			.stack 3;
			.locals 1;

			.descriptor	Ljavacard/framework/APDU;	0.10;

				L0:	aload_0;
					aload_1;
					sconst_2;
					invokevirtual 16;		// get_req(Ljavacard/framework/APDU;S)[B
					astore_2;
					aload_2;
					sconst_5;
					bspush 18;
					bastore;
					aload_2;
					bspush 6;
					bspush 52;
					bastore;
					aload_0;
					aload_1;
					sconst_2;
					invokevirtual 17;		// send_resp(Ljavacard/framework/APDU;S)V
					return;
		}

		.method public status(Ljavacard/framework/APDU;)V 14 {
			.stack 4;
			.locals 5;

			.descriptor	Ljavacard/framework/APDU;	0.10;

				L0:	aload_0;
					aload_1;
					sconst_2;
					invokevirtual 16;		// get_req(Ljavacard/framework/APDU;S)[B
					astore_2;
					aload_0;
					invokevirtual 18;		// bmem()[B
					astore_3;
					bipush 64;
					istore 4;
					sconst_0;
					sstore 6;
				L1:	sload 6;
					s2i;
					iload 4;
					icmp;
					ifge L3;
				L2:	aload_2;
					sconst_5;
					sload 6;
					sadd;
					aload_3;
					sload 6;
					baload;
					bastore;
					sinc 6 1;
					goto L1;
				L3:	aload_0;
					aload_1;
					iload 4;
					i2s;
					invokevirtual 17;		// send_resp(Ljavacard/framework/APDU;S)V
					return;
		}

		.method public setup(Ljavacard/framework/APDU;)V 15 {
			.stack 4;
			.locals 2;

			.descriptor	Ljavacard/framework/APDU;	0.10;

				L0:	aload_0;
					aload_1;
					sconst_2;
					invokevirtual 16;		// get_req(Ljavacard/framework/APDU;S)[B
					astore_2;
					aload_0;
					invokevirtual 19;		// imem()[I
					astore_3;
					aload_2;
					sconst_5;
					aload_3;
					arraylength;
					bspush 8;
					sshr;
					sspush 255;
					sand;
					s2b;
					bastore;
					aload_2;
					bspush 6;
					aload_3;
					arraylength;
					sspush 255;
					sand;
					s2b;
					bastore;
					aload_0;
					aload_1;
					sconst_2;
					invokevirtual 17;		// send_resp(Ljavacard/framework/APDU;S)V
					return;
		}

		.method public read_mem(Ljavacard/framework/APDU;)V 16 {
			.stack 7;
			.locals 10;

			.descriptor	Ljavacard/framework/APDU;	0.10;

				L0:	aload_0;
					aload_1;
					sconst_3;
					invokevirtual 16;		// get_req(Ljavacard/framework/APDU;S)[B
					astore_2;
					aload_0;
					invokevirtual 19;		// imem()[I
					astore_3;
					aload_2;
					sconst_5;
					baload;
					s2i;
					sipush 255;
					iand;
					bipush 8;
					ishl;
					istore 4;
					iload 4;
					aload_2;
					bspush 6;
					baload;
					s2i;
					sipush 255;
					iand;
					ior;
					istore 4;
					aload_2;
					bspush 7;
					baload;
					s2i;
					sipush 255;
					iand;
					istore 6;
					iload 6;
					sipush 252;
					iand;
					istore 6;
					iload 6;
					bipush 64;
					icmp;
					ifle L2;
				L1:	bipush 64;
					istore 6;
				L2:	iconst_0;
					istore 8;
				L3:	iload 8;
					iload 6;
					iconst_2;
					ishr;
					icmp;
					ifge L5;
				L4:	aload_3;
					iload 4;
					iload 8;
					iadd;
					i2s;
					iaload;
					istore 10;
					aload_2;
					iconst_5;
					iload 8;
					iconst_4;
					imul;
					iadd;
					iconst_0;
					iadd;
					i2s;
					iload 10;
					bipush 24;
					ishr;
					sipush 255;
					iand;
					i2b;
					bastore;
					aload_2;
					iconst_5;
					iload 8;
					iconst_4;
					imul;
					iadd;
					iconst_1;
					iadd;
					i2s;
					iload 10;
					bipush 16;
					ishr;
					sipush 255;
					iand;
					i2b;
					bastore;
					aload_2;
					iconst_5;
					iload 8;
					iconst_4;
					imul;
					iadd;
					iconst_2;
					iadd;
					i2s;
					iload 10;
					bipush 8;
					ishr;
					sipush 255;
					iand;
					i2b;
					bastore;
					aload_2;
					iconst_5;
					iload 8;
					iconst_4;
					imul;
					iadd;
					iconst_3;
					iadd;
					i2s;
					iload 10;
					sipush 255;
					iand;
					i2b;
					bastore;
					iinc 8 1;
					goto L3;
				L5:	aload_0;
					aload_1;
					iload 6;
					i2s;
					invokevirtual 17;		// send_resp(Ljavacard/framework/APDU;S)V
					return;
		}

		.method public write_mem(Ljavacard/framework/APDU;)V 17 {
			.stack 6;
			.locals 6;

			.descriptor	Ljavacard/framework/APDU;	0.10;

				L0:	aload_0;
					aload_1;
					bspush 6;
					invokevirtual 16;		// get_req(Ljavacard/framework/APDU;S)[B
					astore_2;
					aload_0;
					invokevirtual 19;		// imem()[I
					astore_3;
					aload_2;
					sconst_5;
					baload;
					s2i;
					sipush 255;
					iand;
					bipush 8;
					ishl;
					istore 4;
					iload 4;
					aload_2;
					bspush 6;
					baload;
					s2i;
					sipush 255;
					iand;
					ior;
					istore 4;
					aload_2;
					bspush 7;
					baload;
					s2i;
					sipush 255;
					iand;
					bipush 24;
					ishl;
					istore 6;
					iload 6;
					aload_2;
					bspush 8;
					baload;
					s2i;
					sipush 255;
					iand;
					bipush 16;
					ishl;
					ior;
					istore 6;
					iload 6;
					aload_2;
					bspush 9;
					baload;
					s2i;
					sipush 255;
					iand;
					bipush 8;
					ishl;
					ior;
					istore 6;
					iload 6;
					aload_2;
					bspush 10;
					baload;
					s2i;
					sipush 255;
					iand;
					ior;
					istore 6;
					aload_3;
					iload 4;
					i2s;
					iload 6;
					iastore;
					aload_2;
					sconst_5;
					iload 6;
					bipush 24;
					ishr;
					sipush 255;
					iand;
					i2b;
					bastore;
					aload_2;
					bspush 6;
					iload 6;
					bipush 16;
					ishr;
					sipush 255;
					iand;
					i2b;
					bastore;
					aload_2;
					bspush 7;
					iload 6;
					bipush 8;
					ishr;
					sipush 255;
					iand;
					i2b;
					bastore;
					aload_2;
					bspush 8;
					iload 6;
					sipush 255;
					iand;
					i2b;
					bastore;
					aload_0;
					aload_1;
					sconst_4;
					invokevirtual 17;		// send_resp(Ljavacard/framework/APDU;S)V
					return;
		}

		.method public cleanup(Ljavacard/framework/APDU;)V 18 {
			.stack 4;
			.locals 2;

			.descriptor	Ljavacard/framework/APDU;	0.10;

				L0:	aload_0;
					aload_1;
					sconst_2;
					invokevirtual 16;		// get_req(Ljavacard/framework/APDU;S)[B
					astore_2;
					aload_0;
					invokevirtual 19;		// imem()[I
					astore_3;
					aload_0;
					invokevirtual 20;		// cleanup()V
					aload_2;
					sconst_5;
					aload_3;
					arraylength;
					bspush 8;
					sshr;
					sspush 255;
					sand;
					s2b;
					bastore;
					aload_2;
					bspush 6;
					aload_3;
					arraylength;
					sspush 255;
					sand;
					s2b;
					bastore;
					aload_0;
					aload_1;
					sconst_2;
					invokevirtual 17;		// send_resp(Ljavacard/framework/APDU;S)V
					return;
		}

		.method public process(Ljavacard/framework/APDU;)V 7 {
			.stack 2;
			.locals 3;

			.descriptor	Ljavacard/framework/APDU;	0.10;

				L0:	aload_0;
					invokevirtual 21;		// selectingApplet()Z
					ifeq L2;
				L1:	return;
				L2:	aload_1;
					invokevirtual 10;		// getBuffer()[B
					astore_2;
					aload_2;
					sconst_4;
					baload;
					sstore_3;
					aload_1;
					invokevirtual 11;		// setIncomingAndReceive()S
					s2b;
					sstore 4;
					sload_3;
					sload 4;
					if_scmpeq L4;
				L3:	sspush 26368;
					invokestatic 12;		// javacard/framework/ISOException.throwIt(S)V
				L4:	aload_2;
					sconst_0;
					baload;
					bspush -128;
					if_scmpeq L6;
				L5:	sspush 28160;
					invokestatic 12;		// javacard/framework/ISOException.throwIt(S)V
				L6:	aload_2;
					sconst_1;
					baload;
					stableswitch L13 16 21 L7 L8 L9 L10 L11 L12;
				L7:	aload_0;
					aload_1;
					invokevirtual 22;		// ping(Ljavacard/framework/APDU;)V
					return;
				L8:	aload_0;
					aload_1;
					invokevirtual 23;		// status(Ljavacard/framework/APDU;)V
					return;
				L9:	aload_0;
					aload_1;
					invokevirtual 24;		// setup(Ljavacard/framework/APDU;)V
					return;
				L10:	aload_0;
					aload_1;
					invokevirtual 25;		// read_mem(Ljavacard/framework/APDU;)V
					return;
				L11:	aload_0;
					aload_1;
					invokevirtual 26;		// write_mem(Ljavacard/framework/APDU;)V
					return;
				L12:	aload_0;
					aload_1;
					invokevirtual 27;		// cleanup(Ljavacard/framework/APDU;)V
					return;
				L13:	sspush 27904;
					invokestatic 12;		// javacard/framework/ISOException.throwIt(S)V
					return;
		}

	}

}
