// converted by version  [v3.1.0]
// on Wed Apr 15 12:45:37 CEST 2020

.package com/se/applets {
	.aid 0xA0:0x0:0x0:0x0:0x62:0x3:0x1:0xC:0x1;
	.version 0.0;

	.imports {
		0xA0:0x0:0x0:0x0:0x62:0x1:0x1 1.8;		//javacard/framework
		0xA0:0x0:0x0:0x0:0x62:0x3:0x1:0xC:0x2 0.0;		//com/se/vulns
		0xA0:0x0:0x0:0x0:0x62:0x2:0x8:0x1:0x1 1.1;		//javacardx/framework/util/intx
		0xA0:0x0:0x0:0x0:0x62:0x0:0x1 1.0;		//java/lang
	}

	.applet {
		0xA0:0x0:0x0:0x0:0x62:0x3:0x1:0xC:0x1:0x1 SEApplet;
	}

	.constantPool {
		// 0
		instanceFieldRef byte[] SEApplet/bmem;
		// 1
		virtualMethodRef 0.3.1()V;		// register()V
		// 2
		.classRef SEApplet;
		// 3
		staticMethodRef SEApplet/<init>()V;
		// 4
		staticMethodRef 1.0.2()[B;		// com/se/vulns/Cast.bmem()[B
		// 5
		staticMethodRef 0.3.0()V;		// javacard/framework/Applet.<init>()V
		// 6
		virtualMethodRef 0.10.1()[B;		// getBuffer()[B
		// 7
		virtualMethodRef 0.10.6()S;		// setIncomingAndReceive()S
		// 8
		staticMethodRef 0.7.1(S)V;		// javacard/framework/ISOException.throwIt(S)V
		// 9
		virtualMethodRef 0.10.7()S;		// setOutgoing()S
		// 10
		virtualMethodRef 0.10.9(S)V;		// setOutgoingLength(S)V
		// 11
		virtualMethodRef 0.10.4(SS)V;		// sendBytes(SS)V
		// 12
		staticMethodRef 0.16.0([BS[BSS)B;		// javacard/framework/Util.arrayCompare([BS[BSS)B
		// 13
		virtualMethodRef SEApplet/find_val([BS)B;
		// 14
		virtualMethodRef SEApplet/get_req(Ljavacard/framework/APDU;S)[B;
			.descriptor	Ljavacard/framework/APDU;	0.10;

		// 15
		virtualMethodRef SEApplet/arrayCopy_oracle([BS[BS)V;
		// 16
		virtualMethodRef SEApplet/send_resp(Ljavacard/framework/APDU;S)V;
			.descriptor	Ljavacard/framework/APDU;	0.10;

		// 17
		staticMethodRef 0.16.7([BSSB)S;		// javacard/framework/Util.arrayFill([BSSB)S
		// 18
		staticMethodRef 0.16.3([BSSB)S;		// javacard/framework/Util.arrayFillNonAtomic([BSSB)S
		// 19
		staticMethodRef 0.16.6([BSS)S;		// javacard/framework/Util.setShort([BSS)S
		// 20
		staticMethodRef 2.0.3([BSI)S;		// javacardx/framework/util/intx/JCint.setInt([BSI)S
		// 21
		virtualMethodRef SEApplet/get_req(Ljavacard/framework/APDU;)[B;
			.descriptor	Ljavacard/framework/APDU;	0.10;

		// 22
		virtualMethodRef SEApplet/arrayCopy_fill([B[BSSI)V;
		// 23
		virtualMethodRef SEApplet/arrayCopy_setshort([B[BSS)V;
		// 24
		virtualMethodRef SEApplet/arrayCopy_setint([B[BSS)V;
		// 25
		virtualMethodRef SEApplet/read_mem(Ljavacard/framework/APDU;)V;
			.descriptor	Ljavacard/framework/APDU;	0.10;

		// 26
		virtualMethodRef SEApplet/write_mem(Ljavacard/framework/APDU;)V;
			.descriptor	Ljavacard/framework/APDU;	0.10;

	}

	.class public SEApplet 0 extends 0.3 {		// extends javacard/framework/Applet

		.fields {
			private byte[] bmem 0;		// [B
			private static final byte SEApplet_CLA = -128;		// B
			private static final byte READ_MEM = 16;		// B
			private static final byte WRITE_MEM = 17;		// B
			private static final short BUFLEN = 64;		// S
		}

		.publicMethodTable 7 14 {
			equals(Ljava/lang/Object;)Z 0;
			register()V 1;
			register([BSB)V 2;
			selectingApplet()Z 3;
			deselect()V 4;
			getShareableInterfaceObject(Ljavacard/framework/AID;B)Ljavacard/framework/Shareable; 5;
			select()Z 6;
			process(Ljavacard/framework/APDU;)V 7;
			bmem()[B 255;
			get_req(Ljavacard/framework/APDU;)[B 255;
			get_req(Ljavacard/framework/APDU;S)[B 255;
			send_resp(Ljavacard/framework/APDU;S)V 255;
			read_mem(Ljavacard/framework/APDU;)V 255;
			write_mem(Ljavacard/framework/APDU;)V 255;
		}

		.packageMethodTable 0 {
			find_val([BS)B;
			arrayCopy_oracle([BS[BS)V;
			arrayCopy_fill([B[BSSI)V;
			arrayCopy_setshort([B[BSS)V;
			arrayCopy_setint([B[BSS)V;
		}

		.method protected <init>()V 0 {
			.stack 1;
			.locals 0;

				L0:	aload_0;
					invokespecial 5;		// javacard/framework/Applet.<init>()V
					aload_0;
					invokevirtual 1;		// register()V
					return;
		}

		.method public static install([BSB)V 1 {
			.stack 2;
			.locals 0;

				L0:	new 2;		// com/se/applets/SEApplet
					dup;
					invokespecial 3;		// com/se/applets/SEApplet.<init>()V
					pop;
					return;
		}

		.method public bmem()[B 8 {
			.stack 2;
			.locals 0;

				L0:	aload_0;
					invokestatic 4;		// com/se/vulns/Cast.bmem()[B
					putfield_a 0;		// reference com/se/applets/SEApplet.bmem
					getfield_a_this 0;		// reference com/se/applets/SEApplet.bmem
					areturn;
		}

		.method public get_req(Ljavacard/framework/APDU;)[B 9 {
			.stack 1;
			.locals 2;

			.descriptor	Ljavacard/framework/APDU;	0.10;

				L0:	aload_1;
					invokevirtual 6;		// getBuffer()[B
					astore_2;
					aload_1;
					invokevirtual 7;		// setIncomingAndReceive()S
					s2b;
					sstore_3;
					aload_2;
					areturn;
		}

		.method public get_req(Ljavacard/framework/APDU;S)[B 10 {
			.stack 2;
			.locals 3;

			.descriptor	Ljavacard/framework/APDU;	0.10;

				L0:	aload_1;
					invokevirtual 6;		// getBuffer()[B
					astore_3;
					aload_3;
					sconst_4;
					baload;
					sstore 4;
					aload_1;
					invokevirtual 7;		// setIncomingAndReceive()S
					s2b;
					sstore 5;
					sload 4;
					sload_2;
					if_scmpne L2;
				L1:	sload 5;
					sload_2;
					if_scmpeq L3;
				L2:	sspush 26368;
					invokestatic 8;		// javacard/framework/ISOException.throwIt(S)V
				L3:	aload_3;
					areturn;
		}

		.method public send_resp(Ljavacard/framework/APDU;S)V 11 {
			.stack 3;
			.locals 1;

			.descriptor	Ljavacard/framework/APDU;	0.10;

				L0:	aload_1;
					invokevirtual 9;		// setOutgoing()S
					sstore_3;
					sload_3;
					sload_2;
					if_scmpge L2;
				L1:	sspush 26368;
					invokestatic 8;		// javacard/framework/ISOException.throwIt(S)V
				L2:	aload_1;
					sload_2;
					s2b;
					invokevirtual 10;		// setOutgoingLength(S)V
					aload_1;
					sconst_5;
					sload_2;
					invokevirtual 11;		// sendBytes(SS)V
					return;
		}

		.method  find_val([BS)B 128 {
			.stack 5;
			.locals 3;

				L0:	sconst_1;
					newarray 11;
					astore_3;
					sconst_0;
					sstore 4;
				L1:	sload 4;
					sspush 256;
					if_scmpge L5;
				L2:	aload_3;
					sconst_0;
					sload 4;
					s2b;
					bastore;
					aload_1;
					sload_2;
					aload_3;
					sconst_0;
					sconst_1;
					invokestatic 12;		// javacard/framework/Util.arrayCompare([BS[BSS)B
					sstore 5;
					sload 5;
					ifne L4;
				L3:	sload 4;
					s2b;
					sreturn;
				L4:	sinc 4 1;
					goto L1;
				L5:	sconst_0;
					sreturn;
		}

		.method  arrayCopy_oracle([BS[BS)V 129 {
			.stack 6;
			.locals 1;

				L0:	sconst_0;
					sstore 5;
				L1:	sload 5;
					sload 4;
					if_scmpge L3;
				L2:	aload_3;
					sload 5;
					aload_0;
					aload_1;
					sload_2;
					sload 5;
					sadd;
					invokevirtual 13;		// find_val([BS)B
					bastore;
					sinc 5 1;
					goto L1;
				L3:	return;
		}

		.method public read_mem(Ljavacard/framework/APDU;)V 12 {
			.stack 6;
			.locals 12;

			.descriptor	Ljavacard/framework/APDU;	0.10;

				L0:	aload_0;
					aload_1;
					sconst_4;
					invokevirtual 14;		// get_req(Ljavacard/framework/APDU;S)[B
					astore_2;
					aload_2;
					sconst_5;
					baload;
					s2i;
					sipush 255;
					iand;
					bipush 8;
					ishl;
					istore_3;
					iload_3;
					aload_2;
					bspush 6;
					baload;
					s2i;
					sipush 255;
					iand;
					ior;
					istore_3;
					aload_2;
					bspush 7;
					baload;
					s2i;
					sipush 255;
					iand;
					istore 5;
					aload_2;
					bspush 8;
					baload;
					s2i;
					sipush 255;
					iand;
					istore 7;
					iload 5;
					bipush 64;
					icmp;
					ifle L2;
				L1:	bipush 64;
					istore 5;
				L2:	invokestatic 4;		// com/se/vulns/Cast.bmem()[B
					astore 9;
					iload 5;
					i2s;
					newarray 11;
					astore 10;
					aload_0;
					aload 9;
					iload_3;
					i2s;
					aload 10;
					iload 5;
					i2s;
					invokevirtual 15;		// arrayCopy_oracle([BS[BS)V
					iconst_0;
					istore 11;
				L3:	iload 11;
					iload 5;
					icmp;
					ifge L5;
				L4:	aload 10;
					iload 11;
					i2s;
					baload;
					sstore 13;
					aload_2;
					iconst_5;
					iload 11;
					iadd;
					i2s;
					sload 13;
					bastore;
					iinc 11 1;
					goto L3;
				L5:	aload_0;
					aload_1;
					iload 5;
					i2s;
					invokevirtual 16;		// send_resp(Ljavacard/framework/APDU;S)V
					return;
		}

		.method  arrayCopy_fill([B[BSSI)V 130 {
			.stack 4;
			.locals 2;

				L0:	sconst_0;
					sstore 7;
				L1:	sload 7;
					sload 4;
					if_scmpge L6;
				L2:	aload_1;
					sload 7;
					baload;
					sstore 8;
					iload 5;
					iconst_0;
					icmp;
					ifne L4;
				L3:	aload_2;
					sload_3;
					sload 7;
					sadd;
					sconst_1;
					sload 8;
					invokestatic 17;		// javacard/framework/Util.arrayFill([BSSB)S
					pop;
					goto L5;
				L4:	aload_2;
					sload_3;
					sload 7;
					sadd;
					sconst_1;
					sload 8;
					invokestatic 18;		// javacard/framework/Util.arrayFillNonAtomic([BSSB)S
					pop;
				L5:	sinc 7 1;
					goto L1;
				L6:	return;
		}

		.method  arrayCopy_setshort([B[BSS)V 131 {
			.stack 4;
			.locals 2;

				L0:	sconst_0;
					sstore 5;
				L1:	sload 5;
					sload 4;
					if_scmpge L3;
				L2:	aload_1;
					sload 5;
					baload;
					sspush 255;
					sand;
					bspush 8;
					sshl;
					sstore 6;
					sload 6;
					aload_1;
					sload 5;
					sconst_1;
					sadd;
					baload;
					sspush 255;
					sand;
					sconst_0;
					sshl;
					sor;
					sstore 6;
					aload_2;
					sload_3;
					sload 5;
					sadd;
					sload 6;
					invokestatic 19;		// javacard/framework/Util.setShort([BSS)S
					pop;
					sinc 5 2;
					goto L1;
				L3:	return;
		}

		.method  arrayCopy_setint([B[BSS)V 132 {
			.stack 6;
			.locals 3;

				L0:	sconst_0;
					sstore 5;
				L1:	sload 5;
					sload 4;
					if_scmpge L3;
				L2:	aload_1;
					sload 5;
					baload;
					s2i;
					sipush 255;
					iand;
					bipush 24;
					ishl;
					istore 6;
					iload 6;
					aload_1;
					sload 5;
					sconst_1;
					sadd;
					baload;
					s2i;
					sipush 255;
					iand;
					bipush 16;
					ishl;
					ior;
					istore 6;
					iload 6;
					aload_1;
					sload 5;
					sconst_2;
					sadd;
					baload;
					s2i;
					sipush 255;
					iand;
					bipush 8;
					ishl;
					ior;
					istore 6;
					iload 6;
					aload_1;
					sload 5;
					sconst_3;
					sadd;
					baload;
					s2i;
					sipush 255;
					iand;
					iconst_0;
					ishl;
					ior;
					istore 6;
					aload_2;
					sload_3;
					sload 5;
					sadd;
					iload 6;
					invokestatic 20;		// javacardx/framework/util/intx/JCint.setInt([BSI)S
					pop;
					sinc 5 4;
					goto L1;
				L3:	return;
		}

		.method public write_mem(Ljavacard/framework/APDU;)V 13 {
			.stack 7;
			.locals 12;

			.descriptor	Ljavacard/framework/APDU;	0.10;

				L0:	aload_0;
					aload_1;
					invokevirtual 21;		// get_req(Ljavacard/framework/APDU;)[B
					astore_2;
					aload_2;
					sconst_4;
					baload;
					sstore_3;
					sload_3;
					sconst_4;
					if_scmpge L2;
				L1:	sspush 26368;
					invokestatic 8;		// javacard/framework/ISOException.throwIt(S)V
				L2:	aload_2;
					sconst_5;
					baload;
					s2i;
					sipush 255;
					iand;
					bipush 8;
					ishl;
					istore 4;
					iload 4;
					aload_2;
					bspush 6;
					baload;
					s2i;
					sipush 255;
					iand;
					ior;
					istore 4;
					aload_2;
					bspush 7;
					baload;
					s2i;
					sipush 255;
					iand;
					istore 6;
					aload_2;
					bspush 8;
					baload;
					s2i;
					sipush 255;
					iand;
					istore 8;
					iload 6;
					bipush 64;
					icmp;
					ifle L4;
				L3:	bipush 64;
					istore 6;
				L4:	iload 6;
					iconst_4;
					iadd;
					sload_3;
					s2i;
					icmp;
					ifle L6;
				L5:	sspush 26368;
					invokestatic 8;		// javacard/framework/ISOException.throwIt(S)V
				L6:	iload 6;
					i2s;
					newarray 11;
					astore 10;
					iconst_0;
					istore 11;
				L7:	iload 11;
					iload 6;
					icmp;
					ifge L9;
				L8:	aload_2;
					bipush 9;
					iload 11;
					iadd;
					i2s;
					baload;
					sstore 13;
					aload 10;
					iload 11;
					i2s;
					sload 13;
					bastore;
					iinc 11 1;
					goto L7;
				L9:	invokestatic 4;		// com/se/vulns/Cast.bmem()[B
					astore 11;
					iload 8;
					itableswitch L13 0 3 L10 L10 L11 L12;
				L10:	aload_0;
					aload 10;
					aload 11;
					iload 4;
					i2s;
					iload 6;
					i2s;
					iload 8;
					invokevirtual 22;		// arrayCopy_fill([B[BSSI)V
					goto L13;
				L11:	aload_0;
					aload 10;
					aload 11;
					iload 4;
					i2s;
					iload 6;
					i2s;
					invokevirtual 23;		// arrayCopy_setshort([B[BSS)V
					goto L13;
				L12:	aload_0;
					aload 10;
					aload 11;
					iload 4;
					i2s;
					iload 6;
					i2s;
					invokevirtual 24;		// arrayCopy_setint([B[BSS)V
				L13:	aload_0;
					aload_1;
					sconst_0;
					invokevirtual 16;		// send_resp(Ljavacard/framework/APDU;S)V
					return;
		}

		.method public process(Ljavacard/framework/APDU;)V 7 {
			.stack 2;
			.locals 1;

			.descriptor	Ljavacard/framework/APDU;	0.10;

				L0:	aload_1;
					invokevirtual 6;		// getBuffer()[B
					astore_2;
					aload_2;
					sconst_0;
					baload;
					bspush -128;
					if_scmpeq L2;
				L1:	sspush 28160;
					invokestatic 8;		// javacard/framework/ISOException.throwIt(S)V
				L2:	aload_2;
					sconst_1;
					baload;
					slookupswitch L5 2 16 L3 17 L4;
				L3:	aload_0;
					aload_1;
					invokevirtual 25;		// read_mem(Ljavacard/framework/APDU;)V
					return;
				L4:	aload_0;
					aload_1;
					invokevirtual 26;		// write_mem(Ljavacard/framework/APDU;)V
					return;
				L5:	sspush 27904;
					invokestatic 8;		// javacard/framework/ISOException.throwIt(S)V
					return;
		}

	}

}
